[{"language":"HTML","time":"26","chart_bgcolor":"#0345ec"},{"language":"CSS","time":"12","chart_bgcolor":"#0f71bd"},{"language":"JavaScript","time":"20","chart_bgcolor":"#20bdde"},{"language":"PHP","time":"19","chart_bgcolor":"#3ccefe"},{"language":"Laravel","time":"11","chart_bgcolor":"#b29ef3"},{"language":"SQL","time":"7","chart_bgcolor":"#6d46ec"},{"language":"SHELL","time":"21","chart_bgcolor":"#4a17ef"},{"language":"\u60c5\u5831\u30b7\u30b9\u30c6\u30e0\u57fa\u790e\u77e5\u8b58\uff08\u305d\u306e\u4ed6\uff09","time":"9","chart_bgcolor":"#3105c0"}]